{
  "annotations": {
    "list": [
      {
        "builtIn": 1,
        "datasource": {
          "type": "grafana",
          "uid": "-- Grafana --"
        },
        "enable": true,
        "hide": true,
        "iconColor": "rgba(0, 211, 255, 1)",
        "name": "Annotations & Alerts",
        "target": {
          "limit": 100,
          "matchAny": false,
          "tags": [],
          "type": "dashboard"
        },
        "type": "dashboard"
      }
    ]
  },
  "editable": true,
  "fiscalYearStartMonth": 0,
  "graphTooltip": 0,
  "id": 9,
  "links": [
    {
      "asDropdown": false,
      "icon": "external link",
      "includeVars": false,
      "keepTime": false,
      "tags": [],
      "targetBlank": true,
      "title": "TOSIT-IO/tdp-observability ",
      "tooltip": "GitHub repository",
      "type": "link",
      "url": "https://github.com/TOSIT-IO/tdp-observability"
    },
    {
      "asDropdown": false,
      "icon": "external link",
      "includeVars": false,
      "keepTime": false,
      "tags": [],
      "targetBlank": true,
      "title": "Made with ❤️ by TOSIT",
      "tooltip": "TOSIT website",
      "type": "link",
      "url": "https://tosit.io/"
    }
  ],
  "liveNow": false,
  "panels": [
    {
      "datasource": {
        "type": "loki",
        "uid": "${DS_LOKI}"
      },
      "gridPos": {
        "h": 21,
        "w": 24,
        "x": 0,
        "y": 0
      },
      "id": 2,
      "options": {
        "dedupStrategy": "numbers",
        "enableLogDetails": true,
        "prettifyLogMessage": false,
        "showCommonLabels": false,
        "showLabels": false,
        "showTime": false,
        "sortOrder": "Descending",
        "wrapLogMessage": false
      },
      "targets": [
        {
          "datasource": {
            "type": "loki",
            "uid": "${DS_LOKI}"
          },
          "editorMode": "builder",
          "expr": "{job=~\"$job\", instance=~\"$instance\", filename=~\"$filename\"} |= `$text`",
          "queryType": "range",
          "refId": "A"
        }
      ],
      "title": "Job: ${job} - host: ${instance} - file : ${filename}",
      "type": "logs"
    }
  ],
  "schemaVersion": 37,
  "style": "dark",
  "tags": [
    "cluster",
    "tdp",
    "logs",
    "loki"
  ],
  "templating": {
    "list": [
      {
        "current": {
          "selected": false,
          "text": "TDP Loki",
          "value": "TDP Loki"
        },
        "hide": 0,
        "includeAll": false,
        "label": "Datasource",
        "multi": false,
        "name": "DS_LOKI",
        "options": [],
        "query": "loki",
        "queryValue": "",
        "refresh": 1,
        "regex": "",
        "skipUrlSync": false,
        "type": "datasource"
      },
      {
        "allValue": ".*logs$",
        "current": {
          "selected": true,
          "text": "All",
          "value": "$__all"
        },
        "datasource": {
          "type": "loki",
          "uid": "${DS_LOKI}"
        },
        "definition": "",
        "hide": 0,
        "includeAll": true,
        "label": "Application",
        "multi": false,
        "name": "job",
        "options": [],
        "query": {
          "label": "job",
          "refId": "LokiVariableQueryEditor-VariableQuery",
          "stream": "",
          "type": 1
        },
        "refresh": 1,
        "regex": "/.*logs$/",
        "skipUrlSync": false,
        "sort": 0,
        "type": "query"
      },
      {
        "allValue": ".+",
        "current": {
          "selected": false,
          "text": "All",
          "value": "$__all"
        },
        "datasource": {
          "type": "loki",
          "uid": "${DS_LOKI}"
        },
        "definition": "",
        "hide": 0,
        "includeAll": true,
        "label": "Host",
        "multi": false,
        "name": "instance",
        "options": [],
        "query": {
          "label": "instance",
          "refId": "LokiVariableQueryEditor-VariableQuery",
          "stream": "{job=~\"$job\"}",
          "type": 1
        },
        "refresh": 1,
        "regex": "",
        "skipUrlSync": false,
        "sort": 1,
        "type": "query"
      },
      {
        "allValue": ".+",
        "current": {
          "selected": false,
          "text": "All",
          "value": "$__all"
        },
        "datasource": {
          "type": "loki",
          "uid": "${DS_LOKI}"
        },
        "definition": "",
        "hide": 0,
        "includeAll": true,
        "label": "Log file",
        "multi": false,
        "name": "filename",
        "options": [],
        "query": {
          "label": "filename",
          "refId": "LokiVariableQueryEditor-VariableQuery",
          "stream": "{job=~\"$job\", instance=~\"$instance\"}",
          "type": 1
        },
        "refresh": 1,
        "regex": "",
        "skipUrlSync": false,
        "sort": 0,
        "type": "query"
      },
      {
        "current": {
          "selected": false,
          "text": "",
          "value": ""
        },
        "hide": 0,
        "label": "Search text",
        "name": "text",
        "options": [
          {
            "selected": true,
            "text": "",
            "value": ""
          }
        ],
        "query": "",
        "skipUrlSync": false,
        "type": "textbox"
      }
    ]
  },
  "time": {
    "from": "now-6h",
    "to": "now"
  },
  "timepicker": {},
  "timezone": "",
  "title": "TDP Cluster logs",
  "uid": "5VgU2IiIkd",
  "version": 1,
  "weekStart": ""
}